drdb/__init__.py
drdb/drdb.py
drdb/schema.py
drdb-0.0.2.dist-info/LICENSE
drdb-0.0.2.dist-info/METADATA
drdb-0.0.2.dist-info/WHEEL
drdb-0.0.2.dist-info/top_level.txt
drdb-0.0.2.dist-info/RECORD
