Metadata-Version: 2.1
Name: drdb
Version: 0.0.2
Summary: Database.
Home-page: https://github.com/DrDataYE/DrDB
Author: DrDataYE
Author-email: drdstaye@gmail.com
Classifier: Programming Language :: Python :: 3
Classifier: Programming Language :: Python :: 3.6
Classifier: Programming Language :: Python :: 3.7
Classifier: Programming Language :: Python :: 3.8
Classifier: Programming Language :: Python :: 3.9
Classifier: Programming Language :: Python :: 3.10
Classifier: Programming Language :: Python :: 3.11
Classifier: License :: OSI Approved :: MIT License
License-File: LICENSE
